docsetviz/__init__.py
docsetviz/main.py
docsetviz/xxx.py
docsetviz/libs/__init__.py
docsetviz/libs/canvas.py
docsetviz/libs/docset_scaner.py
docsetviz/libs/hashable_qlist_widget_item.py
docsetviz/libs/remote_dialog.py
docsetviz/libs/shape.py
docsetviz/libs/tool_bar.py
docsetviz/libs/utils.py
docsetviz/libs/zoom_widget.py
docsetviz-1.1.dist-info/LICENSE
docsetviz-1.1.dist-info/METADATA
docsetviz-1.1.dist-info/WHEEL
docsetviz-1.1.dist-info/entry_points.txt
docsetviz-1.1.dist-info/top_level.txt
docsetviz-1.1.dist-info/RECORD
