Metadata-Version: 2.1
Name: docsetviz
Version: 1.1
Summary: Docset Visualization Tool
Author: yanaenen
License: UNKNOWN
Platform: any
Classifier: Programming Language :: Python :: 3.6
Classifier: Programming Language :: Python :: 3.7
Classifier: Programming Language :: Python :: 3.8
License-File: LICENSE
Requires-Dist: docset
Requires-Dist: numpy
Requires-Dist: opencv-python
Requires-Dist: paramiko
Requires-Dist: PyQt5
